kowabunga/__init__.py
kowabunga/api_client.py
kowabunga/api_response.py
kowabunga/configuration.py
kowabunga/exceptions.py
kowabunga/py.typed
kowabunga/rest.py
kowabunga/api/__init__.py
kowabunga/api/adapter_api.py
kowabunga/api/agent_api.py
kowabunga/api/instance_api.py
kowabunga/api/kaktus_api.py
kowabunga/api/kawaii_api.py
kowabunga/api/kiwi_api.py
kowabunga/api/kompute_api.py
kowabunga/api/konvey_api.py
kowabunga/api/kylo_api.py
kowabunga/api/nfs_api.py
kowabunga/api/pool_api.py
kowabunga/api/project_api.py
kowabunga/api/record_api.py
kowabunga/api/region_api.py
kowabunga/api/subnet_api.py
kowabunga/api/team_api.py
kowabunga/api/template_api.py
kowabunga/api/token_api.py
kowabunga/api/user_api.py
kowabunga/api/vnet_api.py
kowabunga/api/volume_api.py
kowabunga/api/zone_api.py
kowabunga/models/__init__.py
kowabunga/models/adapter.py
kowabunga/models/agent.py
kowabunga/models/api_error_bad_request.py
kowabunga/models/api_error_conflict.py
kowabunga/models/api_error_forbidden.py
kowabunga/models/api_error_insufficient_resource.py
kowabunga/models/api_error_not_found.py
kowabunga/models/api_error_unauthorized.py
kowabunga/models/api_error_unprocessable_entity.py
kowabunga/models/api_token.py
kowabunga/models/cost.py
kowabunga/models/dns_record.py
kowabunga/models/instance.py
kowabunga/models/instance_remote_access.py
kowabunga/models/instance_state.py
kowabunga/models/ip_range.py
kowabunga/models/kaktus.py
kowabunga/models/kaktus_caps.py
kowabunga/models/kaktus_cpu.py
kowabunga/models/kawaii.py
kowabunga/models/kawaii_d_nat_rule.py
kowabunga/models/kawaii_firewall.py
kowabunga/models/kawaii_firewall_egress_rule.py
kowabunga/models/kawaii_firewall_ingress_rule.py
kowabunga/models/kawaii_ip_sec.py
kowabunga/models/kawaii_net_ip.py
kowabunga/models/kawaii_net_ip_zone.py
kowabunga/models/kawaii_vpc_forward_rule.py
kowabunga/models/kawaii_vpc_net_ip_zone.py
kowabunga/models/kawaii_vpc_peering.py
kowabunga/models/kiwi.py
kowabunga/models/kompute.py
kowabunga-0.53.1.dist-info/licenses/LICENSE
kowabunga-0.53.1.dist-info/METADATA
kowabunga-0.53.1.dist-info/WHEEL
kowabunga-0.53.1.dist-info/top_level.txt
kowabunga-0.53.1.dist-info/RECORD
