Metadata-Version: 2.4
Name: kowabunga
Version: 0.53.1
Summary: Kowabunga API
Home-page: https://github.com/kowabunga-cloud/kowabunga-python
Author: The Kowabunga Project
Author-email: maintainers@kowabunga.cloud
License: Apache 2.0
Keywords: OpenAPI,OpenAPI-Generator,Kowabunga API
License-File: LICENSE
Requires-Dist: urllib3<3.0.0,>=1.25.3
Requires-Dist: python-dateutil>=2.8.2
Requires-Dist: pydantic>=2
Requires-Dist: typing-extensions>=4.7.1
Dynamic: author
Dynamic: author-email
Dynamic: description
Dynamic: description-content-type
Dynamic: home-page
Dynamic: keywords
Dynamic: license
Dynamic: license-file
Dynamic: requires-dist
Dynamic: summary
